revolt/__init__.py
revolt/asset.py
revolt/category.py
revolt/channel.py
revolt/client.py
revolt/embed.py
revolt/emoji.py
revolt/enums.py
revolt/errors.py
revolt/file.py
revolt/flags.py
revolt/http.py
revolt/invite.py
revolt/member.py
revolt/message.py
revolt/messageable.py
revolt/permissions.py
revolt/permissions_calculator.py
revolt/py.typed
revolt/role.py
revolt/server.py
revolt/state.py
revolt/user.py
revolt/utils.py
revolt/websocket.py
revolt/ext/__init__.py
revolt/ext/commands/__init__.py
revolt/ext/commands/checks.py
revolt/ext/commands/client.py
revolt/ext/commands/cog.py
revolt/ext/commands/command.py
revolt/ext/commands/context.py
revolt/ext/commands/converters.py
revolt/ext/commands/cooldown.py
revolt/ext/commands/errors.py
revolt/ext/commands/group.py
revolt/ext/commands/help.py
revolt/ext/commands/utils.py
revolt/ext/commands/view.py
revolt/types/__init__.py
revolt/types/category.py
revolt/types/channel.py
revolt/types/embed.py
revolt/types/emoji.py
revolt/types/file.py
revolt/types/gateway.py
revolt/types/http.py
revolt/types/invite.py
revolt/types/member.py
revolt/types/message.py
revolt/types/permissions.py
revolt/types/role.py
revolt/types/server.py
revolt/types/user.py
revolt.py-0.2.0.dist-info/METADATA
revolt.py-0.2.0.dist-info/WHEEL
revolt.py-0.2.0.dist-info/licenses/LICENSE
revolt.py-0.2.0.dist-info/RECORD
