Metadata-Version: 2.1
Name: revolt.py
Version: 0.2.0
Summary: Python wrapper for the revolt.chat API
Project-URL: Homepage, https://github.com/revoltchat/revolt.py
Project-URL: Documentation, https://revoltpy.readthedocs.io/en/latest/
Project-URL: Source Code, https://github.com/revoltchat/revolt.py
Project-URL: Bug Tracker, https://github.com/revoltchat/revolt.py/issues
Author-email: Zomatree <me@zomatree.live>
License-Expression: MIT
License-File: LICENSE
Keywords: api,async,http,websockets,wrapper
Classifier: Development Status :: 4 - Beta
Classifier: Intended Audience :: Developers
Classifier: License :: OSI Approved :: MIT License
Classifier: Programming Language :: Python :: 3
Classifier: Programming Language :: Python :: 3 :: Only
Classifier: Programming Language :: Python :: 3.9
Classifier: Programming Language :: Python :: 3.10
Requires-Python: >=3.9
Requires-Dist: aenum==3.1.*
Requires-Dist: aiohttp==3.8.*
Requires-Dist: typing-extensions>=4.4.0
Requires-Dist: ulid-py==1.1.*
Provides-Extra: docs
Requires-Dist: setuptools==65.4.*; extra == 'docs'
Requires-Dist: sphinx-nameko-theme==0.0.*; extra == 'docs'
Requires-Dist: sphinx-toolbox==3.2.*; extra == 'docs'
Requires-Dist: sphinx==5.2.*; extra == 'docs'
Provides-Extra: speedups
Requires-Dist: msgpack==1.0.*; extra == 'speedups'
Requires-Dist: ujson==5.1.*; extra == 'speedups'
